pychronicles/__init__.py
pychronicles/abstraction.py
pychronicles/chronicle.py
pychronicles/fchronicle.py
pychronicles/mining/chronicle_mining.py
pychronicles/mtlformula.py
pychronicles/pandas_tpatterns.py
pychronicles/timedsequence.py
pychronicles/utils.py
pychronicles-0.1.1.dist-info/METADATA
pychronicles-0.1.1.dist-info/WHEEL
pychronicles-0.1.1.dist-info/RECORD
