Metadata-Version: 2.1
Name: pychronicles
Version: 0.1.1
Summary: A package for chronicle recognition
License: LICENCE
Keywords: data analysis,pattern,timed sequence,temporal data
Author: Thomas Guyet
Author-email: thomas.guyet@inria.fr
Requires-Python: >=3.8,<4.0
Classifier: License :: OSI Approved :: GNU Lesser General Public License v3 (LGPLv3)
Classifier: License :: Other/Proprietary License
Classifier: Operating System :: OS Independent
Classifier: Programming Language :: Python
Classifier: Programming Language :: Python :: 3
Classifier: Programming Language :: Python :: 3.8
Classifier: Programming Language :: Python :: 3.9
Classifier: Programming Language :: Python :: 3.10
Classifier: Programming Language :: Python :: 3.11
Requires-Dist: lark (>=1.1.4,<2.0.0)
Requires-Dist: lazr.restfulclient (>=0.14.5,<0.15.0)
Requires-Dist: lazr.uri (>=1.0.6,<2.0.0)
Requires-Dist: metric-temporal-logic (>=0.4.0,<0.5.0)
Requires-Dist: multiset (>=3.0.1,<4.0.0)
Requires-Dist: numpy (>=1.23.4,<2.0.0)
Requires-Dist: pandas (>=1.5.1,<2.0.0)
Requires-Dist: scipy (>=1.9.3,<2.0.0)
Requires-Dist: typing-extensions (>=4.4.0,<5.0.0)
Project-URL: documentation, https://tguyet.gitlabpages.inria.fr/pychronicles/
Project-URL: homepage, https://gitlab.inria.fr/tguyet/pychronicles
Project-URL: repository, https://gitlab.inria.fr/tguyet/pychronicles
